bqn.cpython-313-darwin.so
pybqn-0.1.1.dist-info/licenses/COPYING
pybqn-0.1.1.dist-info/licenses/LICENSE
pybqn-0.1.1.dist-info/METADATA
pybqn-0.1.1.dist-info/WHEEL
pybqn-0.1.1.dist-info/top_level.txt
pybqn-0.1.1.dist-info/RECORD
