Metadata-Version: 2.4
Name: pybqn
Version: 0.1.1
Author-email: Vanessa McHale <vamchale@gmail.com>
License: Copyright (C) 2023 Vanessa McHale
Project-URL: CBQN, https://github.com/dzaima/CBQN
License-File: LICENSE
License-File: COPYING
Requires-Dist: numpy>=2.0
Dynamic: license-file
